<?xml version="1.0" encoding="utf-8" ?>
<dwsync>
<file name="color-picker.min.css" server="driftwood.dreamhost.com" local="130332837764446542" remote="130300482600000000" Dst="1" />
<file name="color-picker-rtl.css" server="driftwood.dreamhost.com" local="130332837771356937" remote="130312577400000000" Dst="1" />
<file name="color-picker.css" server="driftwood.dreamhost.com" local="130332837763796505" remote="130312577400000000" Dst="1" />
<file name="color-picker-rtl.min.css" server="driftwood.dreamhost.com" local="130332837770126867" remote="130300482600000000" Dst="1" />
<file name="colors.css" server="driftwood.dreamhost.com" local="130332837888303626" remote="130310868600000000" Dst="1" />
<file name="colors.min.css" server="driftwood.dreamhost.com" local="130332837888303626" remote="130312726800000000" Dst="1" />
<file name="colors-rtl.css" server="driftwood.dreamhost.com" local="130332837892193849" remote="130310868600000000" Dst="1" />
<file name="colors-rtl.min.css" server="driftwood.dreamhost.com" local="130332837893583928" remote="130312726800000000" Dst="1" />
<file name="customize-controls.css" server="driftwood.dreamhost.com" local="130332837892923890" remote="130300482600000000" Dst="1" />
<file name="customize-controls.min.css" server="driftwood.dreamhost.com" local="130332837899144246" remote="130300482600000000" Dst="1" />
<file name="customize-controls-rtl.min.css" server="driftwood.dreamhost.com" local="130332837902664448" remote="130300482600000000" Dst="1" />
<file name="customize-controls-rtl.css" server="driftwood.dreamhost.com" local="130332837901994409" remote="130300482600000000" Dst="1" />
<file name="farbtastic.css" server="driftwood.dreamhost.com" local="130332837906934692" remote="130291714800000000" Dst="1" />
<file name="farbtastic-rtl.min.css" server="driftwood.dreamhost.com" local="130332837908274768" remote="130291714800000000" Dst="1" />
<file name="ie.css" server="driftwood.dreamhost.com" local="130332837914405119" remote="130312577400000000" Dst="1" />
<file name="farbtastic-rtl.css" server="driftwood.dreamhost.com" local="130332837908264768" remote="130291714800000000" Dst="1" />
<file name="ie.min.css" server="driftwood.dreamhost.com" local="130332837914415120" remote="130310232600000000" Dst="1" />
<file name="ie-rtl.css" server="driftwood.dreamhost.com" local="130332837917115274" remote="130312577400000000" Dst="1" />
<file name="ie-rtl.min.css" server="driftwood.dreamhost.com" local="130332837921385518" remote="130310232600000000" Dst="1" />
<file name="install.css" server="driftwood.dreamhost.com" local="130332837922835601" remote="130310337000000000" Dst="1" />
<file name="install.min.css" server="driftwood.dreamhost.com" local="130332837922835601" remote="130310337000000000" Dst="1" />
<file name="install-rtl.css" server="driftwood.dreamhost.com" local="130332837928225910" remote="130310337000000000" Dst="1" />
<file name="install-rtl.min.css" server="driftwood.dreamhost.com" local="130332837929445979" remote="130310337000000000" Dst="1" />
<file name="media.min.css" server="driftwood.dreamhost.com" local="130332837934646277" remote="130288455000000000" Dst="1" />
<file name="media.css" server="driftwood.dreamhost.com" local="130332837929455980" remote="130285096200000000" Dst="1" />
<file name="media-rtl.css" server="driftwood.dreamhost.com" local="130332837936166364" remote="130287575400000000" Dst="1" />
<file name="media-rtl.min.css" server="driftwood.dreamhost.com" local="130332837936166364" remote="130288455000000000" Dst="1" />
<file name="wp-admin.min.css" server="driftwood.dreamhost.com" local="130332837953887377" remote="130312726800000000" Dst="1" />
<file name="wp-admin.css" server="driftwood.dreamhost.com" local="130332837955307459" remote="130312499400000000" Dst="1" />
<file name="wp-admin-rtl.css" server="driftwood.dreamhost.com" local="130332837960217739" remote="130312499400000000" Dst="1" />
<file name="wp-admin-rtl.min.css" server="driftwood.dreamhost.com" local="130332837970698339" remote="130312726800000000" Dst="1" />
</dwsync>